balipkg/__init__.py
balipkg/module1/DataPreparation.py
balipkg/module1/TextPreprocessor.py
balipkg/module1/__init__.py
balipkg/module1/balinese_lemmatization/__init__.py
balipkg/module1/balinese_lemmatization/BalineseLemmatization/Lemmatization.py
balipkg/module1/balinese_lemmatization/BalineseLemmatization/LemmatizationRules.py
balipkg/module1/balinese_lemmatization/BalineseLemmatization/__init__.py
balipkg-0.1.5.dist-info/LICENSE
balipkg-0.1.5.dist-info/METADATA
balipkg-0.1.5.dist-info/WHEEL
balipkg-0.1.5.dist-info/top_level.txt
balipkg-0.1.5.dist-info/RECORD
