Metadata-Version: 2.1
Name: balipkg
Version: 0.1.5
Summary: A Python package for Balinese narrative text analysis, including NER, alias clustering, and characterization classification.
Home-page: UNKNOWN
Author: I Made Satria Bimantara
Author-email: satriabimantara.md@gmail.com
License: UNKNOWN
Keywords: Balinese,NLP,Text Analysis,NER,Characterization,Natural Language Processing
Platform: UNKNOWN
Classifier: Development Status :: 3 - Alpha
Classifier: Intended Audience :: Developers
Classifier: Intended Audience :: Science/Research
Classifier: License :: OSI Approved :: MIT License
Classifier: Programming Language :: Python :: 3
Classifier: Programming Language :: Python :: 3.7
Classifier: Programming Language :: Python :: 3.8
Classifier: Programming Language :: Python :: 3.9
Classifier: Programming Language :: Python :: 3.10
Classifier: Programming Language :: Python :: 3.11
Classifier: Operating System :: OS Independent
Classifier: Natural Language :: Indonesian
Classifier: Topic :: Text Processing :: Linguistic
Classifier: Topic :: Scientific/Engineering :: Artificial Intelligence
Requires-Python: >=3.8
Requires-Dist: pandas==1.5.3
Requires-Dist: numpy==1.24.2
